LICENSE
README.md
setup.py
largets/__init__.py
largets.egg-info/PKG-INFO
largets.egg-info/SOURCES.txt
largets.egg-info/dependency_links.txt
largets.egg-info/top_level.txt