Metadata-Version: 2.1
Name: largets
Version: 0.1.0
Summary: A time series library powered by large models.
Home-page: https://github.com/liaoyuhua/largets
Author: Yuhua Liao
Author-email: ml.liaoyuhua@gmail.com
Classifier: License :: OSI Approved :: Apache Software License
Classifier: Programming Language :: Python
Classifier: Programming Language :: Python :: 3
Requires-Python: >=3.8.0
License-File: LICENSE
